paperstream/__init__.py
paperstream/__main__.py
paperstream/create_diary.py
paperstream/encode_diary.py
paperstream/extract_framed_area.py
paperstream/log_configuration.ini
paperstream/marking_server.py
paperstream/paperstream.spec
paperstream/input/1_diaries_to_create/P01.pdf
paperstream/input/1_diaries_to_create/P02.pdf
paperstream/input/1_diaries_to_create/P03.pdf
paperstream/input/1_diaries_to_create/resources/FreeSansLocal.ttf
paperstream/input/1_diaries_to_create/resources/corner_bl.png
paperstream/input/1_diaries_to_create/resources/corner_br.png
paperstream/input/1_diaries_to_create/resources/corner_ul.png
paperstream/input/1_diaries_to_create/resources/corner_ur.png
paperstream/input/1_diaries_to_create/resources/logo1.png
paperstream/input/2_template_to_encode/example_template.png
paperstream/input/3_diaries_to_encode/example_diary_png.zip
paperstream/input/3_diaries_to_encode/example_diary_tif.tif
paperstream/output/created_diaries/.gitkeep
paperstream/output/encoded_diaries/.gitkeep
paperstream/output/temporal/.gitkeep
paperstream/static/.eslintrc.js
paperstream/static/async.min.js
paperstream/static/create.html
paperstream/static/create.js
paperstream/static/dropzone.css
paperstream/static/dropzone.js
paperstream/static/encode.html
paperstream/static/encode.js
paperstream/static/fabric.js
paperstream/static/general.css
paperstream/static/index.html
paperstream/static/jquery-3.2.1.js
paperstream/static/jquery.csv.js
paperstream/static/landingPage.js
paperstream/static/loadingoverlay.min.js
paperstream/static/moment.min.js
paperstream/static/noty.css
paperstream/static/noty.js
paperstream/static/package.json
paperstream/static/template.png
paperstream/static/w3.css
paperstream/static/downloads/.gitkeep
paperstream/static/fonts/oxygen-v7-latin-regular.woff
paperstream/static/fonts/oxygen-v7-latin-regular.woff2
paperstream-1.1.0.dist-info/entry_points.txt
paperstream-1.1.0.dist-info/LICENSE
paperstream-1.1.0.dist-info/WHEEL
paperstream-1.1.0.dist-info/METADATA
paperstream-1.1.0.dist-info/RECORD
