Metadata-Version: 1.2
Name: paperstream
Version: 1.1.0
Summary: PaperStream web app. Create and encode paper diaries or surveys automatically
Home-page: https://paperstream.netlify.com
License: UNKNOWN
Author: Julio Vega
Author-email: julio.vega@protonmail.com
Requires-Python: >=3.6
Classifier: License :: OSI Approved :: MIT License
Classifier: Intended Audience :: Science/Research
Classifier: Operating System :: Microsoft :: Windows :: Windows 10
Classifier: Operating System :: Microsoft :: Windows :: Windows 7
Classifier: Operating System :: MacOS
Classifier: Operating System :: Unix
Classifier: Programming Language :: Python :: 3 :: Only
Classifier: Topic :: Scientific/Engineering :: Human Machine Interfaces
Classifier: Topic :: Scientific/Engineering :: Medical Science Apps.
Requires-Dist: opencv_python (>=3.3.0.10)
Requires-Dist: waitress (>=1.0.2)
Requires-Dist: falcon (>=1.4.1)
Requires-Dist: numpy (>=1.12.1)
Requires-Dist: falcon_multipart (>=0.2.0)
Requires-Dist: Pillow (>=4.3.0)
Requires-Dist: PyPDF2 (>=1.26.0)
Requires-Dist: reportlab (>=3.4.0)
Requires-Dist: natsort (>=5.1.1)
